{"2":[{"Lines":"108","Lon":21.073349,"VehicleNumber":"1020","Time":"2019-12-17 19:06:17","Lat":52.180119,"Brigade":"2"},{"Lines":"108","Lon":21.073349,"VehicleNumber":"1020","Time":"2019-12-17 19:06:17","Lat":52.180119,"Brigade":"2"},{"Lines":"108","Lon":21.071249,"VehicleNumber":"1020","Time":"2019-12-17 19:07:35","Lat":52.180119,"Brigade":"2"},{"Lines":"108","Lon":21.071249,"VehicleNumber":"1020","Time":"2019-12-17 19:07:35","Lat":52.180119,"Brigade":"2"}],"5":[{"Lines":"108","Lon":21.077654,"VehicleNumber":"1028","Time":"2019-12-17 19:07:08","Lat":52.182682,"Brigade":"5"},{"Lines":"108","Lon":21.077698,"VehicleNumber":"1028","Time":"2019-12-17 19:07:20","Lat":52.182716,"Brigade":"5"},{"Lines":"108","Lon":21.077698,"VehicleNumber":"1028","Time":"2019-12-17 19:07:20","Lat":52.182716,"Brigade":"5"},{"Lines":"108","Lon":21.079424,"VehicleNumber":"1028","Time":"2019-12-17 19:07:40","Lat":52.183777,"Brigade":"5"}],"53":[{"Lines":"108","Lon":21.033159,"VehicleNumber":"1035","Time":"2019-12-17 19:05:55","Lat":52.227688,"Brigade":"53"},{"Lines":"108","Lon":21.033159,"VehicleNumber":"1035","Time":"2019-12-17 19:05:55","Lat":52.227688,"Brigade":"53"},{"Lines":"108","Lon":21.03216,"VehicleNumber":"1035","Time":"2019-12-17 19:06:11","Lat":52.228619,"Brigade":"53"},{"Lines":"108","Lon":21.03216,"VehicleNumber":"1035","Time":"2019-12-17 19:06:11","Lat":52.228619,"Brigade":"53"},{"Lines":"108","Lon":21.03216,"VehicleNumber":"1035","Time":"2019-12-17 19:06:11","Lat":52.228619,"Brigade":"53"},{"Lines":"108","Lon":21.03216,"VehicleNumber":"1035","Time":"2019-12-17 19:06:11","Lat":52.228619,"Brigade":"53"},{"Lines":"108","Lon":21.030546,"VehicleNumber":"1035","Time":"2019-12-17 19:06:51","Lat":52.230263,"Brigade":"53"},{"Lines":"108","Lon":21.030546,"VehicleNumber":"1035","Time":"2019-12-17 19:06:51","Lat":52.230263,"Brigade":"53"},{"Lines":"108","Lon":21.029634,"VehicleNumber":"1035","Time":"2019-12-17 19:07:05","Lat":52.230186,"Brigade":"53"},{"Lines":"108","Lon":21.029631,"VehicleNumber":"1035","Time":"2019-12-17 19:07:17","Lat":52.230179,"Brigade":"53"},{"Lines":"108","Lon":21.028181,"VehicleNumber":"1035","Time":"2019-12-17 19:07:33","Lat":52.229919,"Brigade":"53"},{"Lines":"108","Lon":21.028181,"VehicleNumber":"1035","Time":"2019-12-17 19:07:33","Lat":52.229919,"Brigade":"53"}],"51":[{"Lines":"108","Lon":21.0383,"VehicleNumber":"1036","Time":"2019-12-17 19:05:55","Lat":52.176575,"Brigade":"51"},{"Lines":"108","Lon":21.0383,"VehicleNumber":"1036","Time":"2019-12-17 19:05:55","Lat":52.176575,"Brigade":"51"},{"Lines":"108","Lon":21.0383,"VehicleNumber":"1036","Time":"2019-12-17 19:05:55","Lat":52.176575,"Brigade":"51"},{"Lines":"108","Lon":21.039114,"VehicleNumber":"1036","Time":"2019-12-17 19:06:26","Lat":52.176392,"Brigade":"51"},{"Lines":"108","Lon":21.039114,"VehicleNumber":"1036","Time":"2019-12-17 19:06:26","Lat":52.176392,"Brigade":"51"},{"Lines":"108","Lon":21.039114,"VehicleNumber":"1036","Time":"2019-12-17 19:06:26","Lat":52.176392,"Brigade":"51"},{"Lines":"108","Lon":21.039108,"VehicleNumber":"1036","Time":"2019-12-17 19:06:42","Lat":52.176414,"Brigade":"51"},{"Lines":"108","Lon":21.039108,"VehicleNumber":"1036","Time":"2019-12-17 19:06:42","Lat":52.176414,"Brigade":"51"},{"Lines":"108","Lon":21.039108,"VehicleNumber":"1036","Time":"2019-12-17 19:06:42","Lat":52.176414,"Brigade":"51"},{"Lines":"108","Lon":21.03953,"VehicleNumber":"1036","Time":"2019-12-17 19:07:12","Lat":52.1763,"Brigade":"51"},{"Lines":"108","Lon":21.03953,"VehicleNumber":"1036","Time":"2019-12-17 19:07:12","Lat":52.1763,"Brigade":"51"},{"Lines":"108","Lon":21.03953,"VehicleNumber":"1036","Time":"2019-12-17 19:07:12","Lat":52.1763,"Brigade":"51"}],"56":[{"Lines":"108","Lon":21.048504,"VehicleNumber":"1038","Time":"2019-12-17 19:05:41","Lat":52.177731,"Brigade":"56"},{"Lines":"108","Lon":21.049252,"VehicleNumber":"1038","Time":"2019-12-17 19:05:59","Lat":52.177872,"Brigade":"56"},{"Lines":"108","Lon":21.051405,"VehicleNumber":"1038","Time":"2019-12-17 19:06:15","Lat":52.17889,"Brigade":"56"},{"Lines":"108","Lon":21.052479,"VehicleNumber":"1038","Time":"2019-12-17 19:06:23","Lat":52.179558,"Brigade":"56"},{"Lines":"108","Lon":21.052479,"VehicleNumber":"1038","Time":"2019-12-17 19:06:23","Lat":52.179558,"Brigade":"56"},{"Lines":"108","Lon":21.052479,"VehicleNumber":"1038","Time":"2019-12-17 19:06:23","Lat":52.179558,"Brigade":"56"},{"Lines":"108","Lon":21.053734,"VehicleNumber":"1038","Time":"2019-12-17 19:06:44","Lat":52.180325,"Brigade":"56"},{"Lines":"108","Lon":21.053734,"VehicleNumber":"1038","Time":"2019-12-17 19:06:44","Lat":52.180325,"Brigade":"56"},{"Lines":"108","Lon":21.053734,"VehicleNumber":"1038","Time":"2019-12-17 19:06:44","Lat":52.180325,"Brigade":"56"},{"Lines":"108","Lon":21.053734,"VehicleNumber":"1038","Time":"2019-12-17 19:06:44","Lat":52.180325,"Brigade":"56"},{"Lines":"108","Lon":21.054701,"VehicleNumber":"1038","Time":"2019-12-17 19:07:26","Lat":52.180969,"Brigade":"56"},{"Lines":"108","Lon":21.054701,"VehicleNumber":"1038","Time":"2019-12-17 19:07:26","Lat":52.180969,"Brigade":"56"}],"4":[{"Lines":"108","Lon":21.047068,"VehicleNumber":"1065","Time":"2019-12-17 19:07:02","Lat":52.212776,"Brigade":"4"},{"Lines":"108","Lon":21.046316,"VehicleNumber":"1065","Time":"2019-12-17 19:07:19","Lat":52.214642,"Brigade":"4"},{"Lines":"108","Lon":21.046085,"VehicleNumber":"1065","Time":"2019-12-17 19:07:27","Lat":52.215321,"Brigade":"4"},{"Lines":"108","Lon":21.046085,"VehicleNumber":"1065","Time":"2019-12-17 19:07:27","Lat":52.215321,"Brigade":"4"}]}